binance_futures_async/__init__.py
binance_futures_async/client.py
binance_futures_async/exceptions.py
binance_futures_async/utils.py
binance_futures_async/auth/__init__.py
binance_futures_async/auth/auth_factory.py
binance_futures_async/auth/base.py
binance_futures_async/auth/ed25519.py
binance_futures_async/auth/hmac.py
binance_futures_async/auth/rsa.py
binance_futures_async/market_streams/__init__.py
binance_futures_async/market_streams/market_service.py
binance_futures_async/market_streams/market_streams.py
binance_futures_async/user_data_streams/__init__.py
binance_futures_async/user_data_streams/user_data_stream_api.py
binance_futures_async/user_data_streams/user_data_stream_infrastructure.py
binance_futures_async/websocket_api/__init__.py
binance_futures_async/websocket_api/account_info.py
binance_futures_async/websocket_api/market_data.py
binance_futures_async/websocket_api/order_preparation.py
binance_futures_async/websocket_api/websocket_manager.py
binance_futures_async/websocket_api/websocket_service.py
binance_futures_async-0.1.1.dist-info/METADATA
binance_futures_async-0.1.1.dist-info/WHEEL
binance_futures_async-0.1.1.dist-info/licenses/LICENSE
binance_futures_async-0.1.1.dist-info/RECORD
