Metadata-Version: 2.4
Name: binance-futures-async
Version: 0.1.1
Summary: A high-performance, asynchronous Python library for Binance USD-M Futures WebSocket API
Project-URL: Homepage, https://github.com/mumtazkahn/binance-futures-async
Project-URL: Documentation, https://github.com/mumtazkahn/binance-futures-async/tree/main/docs
Project-URL: Repository, https://github.com/mumtazkahn/binance-futures-async
Author-email: mumtazkahn <mumtazz1993@gmail.com>
License-File: LICENSE
Keywords: async,asyncio,binance,cryptocurrency,futures,trading,websocket
Classifier: Development Status :: 4 - Beta
Classifier: Framework :: AsyncIO
Classifier: Intended Audience :: Developers
Classifier: Intended Audience :: Financial and Insurance Industry
Classifier: License :: OSI Approved :: MIT License
Classifier: Operating System :: OS Independent
Classifier: Programming Language :: Python :: 3
Classifier: Programming Language :: Python :: 3.7
Classifier: Programming Language :: Python :: 3.8
Classifier: Programming Language :: Python :: 3.9
Classifier: Programming Language :: Python :: 3.10
Classifier: Programming Language :: Python :: 3.11
Classifier: Topic :: Office/Business :: Financial :: Investment
Classifier: Topic :: Software Development :: Libraries :: Python Modules
Requires-Python: >=3.7
Requires-Dist: aiohttp>=3.8.0
Requires-Dist: cryptography>=3.4.0
